cliwrap/__init__.py
cliwrap/cliwrap.py
cliwrap/utils.py
cliwrap-0.2.1.dist-info/LICENSE
cliwrap-0.2.1.dist-info/WHEEL
cliwrap-0.2.1.dist-info/METADATA
cliwrap-0.2.1.dist-info/RECORD
